pmercury/LICENSE
pmercury/MANIFEST.in
pmercury/README.md
pmercury/__init__.py
pmercury/config.yaml
pmercury/pmercury
pmercury/requirements.txt
pmercury/protocols/__init__.py
pmercury/protocols/dhcp.py
pmercury/protocols/dtls.py
pmercury/protocols/dtls_server.py
pmercury/protocols/http.py
pmercury/protocols/http2.py
pmercury/protocols/http_server.py
pmercury/protocols/iquic.py
pmercury/protocols/protocol.py
pmercury/protocols/ssh.py
pmercury/protocols/tcp.py
pmercury/protocols/tls.py
pmercury/protocols/tls_certificate.py
pmercury/protocols/tls_certificate_full.py
pmercury/protocols/tls_decrypt.py
pmercury/protocols/tls_server.py
pmercury/resources/app_families.txt
pmercury/resources/app_families_strict.txt
pmercury/resources/domain_indicators.json.gz
pmercury/resources/fingerprint-db-http-os.json.gz
pmercury/resources/fingerprint-db-tcp-os.json.gz
pmercury/resources/fingerprint-db-tls-os.json.gz
pmercury/resources/fingerprint_db.json.gz
pmercury/resources/fingerprint_db_tcp.json.gz
pmercury/resources/implementation_date_cs.json.gz
pmercury/resources/implementation_date_ext.json.gz
pmercury/resources/os_detection_model.json
pmercury/resources/public_suffix_list.dat.gz
pmercury/resources/pyasn.db
pmercury/resources/transition_probs.csv.gz
pmercury/resources/equivalence-classes/eqv_class_ip.json.gz
pmercury/resources/equivalence-classes/eqv_class_ip_as.json.gz
pmercury/resources/equivalence-classes/eqv_class_port.json.gz
pmercury/resources/equivalence-classes/eqv_class_port_applications.json.gz
pmercury/resources/equivalence-classes/eqv_class_sni.json.gz
pmercury/test/__init__.py
pmercury/test/pmercury_accuracy.py
pmercury/test/pmercury_performance.py
pmercury/utils/__init__.py
pmercury/utils/cert_constants.py
pmercury/utils/config_parser.py
pmercury/utils/contextual_info.py
pmercury/utils/endpoint.py
pmercury/utils/eqv_classes.py
pmercury/utils/http2_constants.py
pmercury/utils/os_detection.py
pmercury/utils/packet_proc.py
pmercury/utils/pmercury_utils.py
pmercury-0.5.2.44.dist-info/LICENSE
pmercury-0.5.2.44.dist-info/METADATA
pmercury-0.5.2.44.dist-info/WHEEL
pmercury-0.5.2.44.dist-info/top_level.txt
pmercury-0.5.2.44.dist-info/RECORD
