Metadata-Version: 2.1
Name: pmercury
Version: 0.5.2.44
Summary: Python tool for network (TLS, etc.) fingerprinting
Home-page: https://github.com/cisco/mercury/
Author: Blake Anderson
Author-email: blake.anderson@cisco.com
License: UNKNOWN
Keywords: tls fingerprinting network traffic analysis
Platform: UNKNOWN
Classifier: Development Status :: 3 - Alpha
Classifier: Programming Language :: Python :: 3 :: Only
Classifier: Topic :: System :: Networking :: Monitoring
Classifier: Topic :: Security
Requires-Python: >=3.6.0
Requires-Dist: cryptography
Requires-Dist: hpack
Requires-Dist: pyasn
Requires-Dist: pypcap
Requires-Dist: pyyaml
